ManojProj/02-Iterators and Generators Homework.ipynb
ManojProj/08-Built-in Functions Assessment Test.ipynb
ManojProj/__init__.py
ManojProj/bank
ManojProj/first.ipynb
ManojProj/first.py
ManojProj/first2.py
ManojProj/print_dir.py
ManojProj/test_arthematic.py
ManojProj/test_first.py
ManojProj/.ipynb_checkpoints/02-Iterators and Generators Homework-checkpoint.ipynb
ManojProj/.ipynb_checkpoints/08-Built-in Functions Assessment Test-checkpoint.ipynb
ManojProj/.ipynb_checkpoints/first-checkpoint.ipynb
ManojProj/.ipynb_checkpoints/first-checkpoint.py
ManojProj/calc/__init__.py
ManojProj/calc/math/__init__.py
ManojProj/calc/math/arthematic.py
ManojProj/calc/string/__init__.py
ManojProj/calc/string/strops.py
ManojProj/subproj1/__init__.py
ManojProj/subproj1/first.py
ManojProj/tests/__init__.py
ManojProj/tests/first.py
ManojProj/tests/test_arthematic.py
manojproj-0.1.0.dist-info/METADATA
manojproj-0.1.0.dist-info/WHEEL
manojproj-0.1.0.dist-info/entry_points.txt
manojproj-0.1.0.dist-info/RECORD
